{"Territory of the":"","undefined":"^ English does not have de jure status in Cocos (Keeling) Island and in Australia, but it is the de facto language of communication in government.","Status":"External Territory","Capital":"West Island","Largest village":"Bantam (Home Island)","Official languages":"None[a]","Mother languages":"Malay, English","Demonym":"Cocossian","Sovereign state":"Australia","Government":"Federal constitutional monarchy","Monarch":"Elizabeth II","Governor-General of the Commonwealth of Australia":"Sir Peter Cosgrove","Administrator":"Barry Haase","Shire President":"Aindil Minkom","Territory of Australia":"","Annexed by the":"1857","Transferred to":"1955","Area":"","Total":"14 km2 (5.4 sq mi)","Water (%)":"0","Population":"","July 2014 estimate":"596[1] (237)","Density":"43/km2 (111.4/sq mi) (n/a)","Currency":"Australian dollar (AUD)","Time zone":"CCT (UTC+06:30)","Calling code":"61 891","ISO 3166 code":"CC","Internet TLD":".cc"}