{"State of Eritrea":"","undefined":"","Capital":"Asmara","Official languages":"None[1] (see working languages)","Recognised national languages":"Tigrinya","Working languages":"Tigrinya[4]","Ethnic groups (2012[5])":"55% Tigrinya","Demonym":"Eritrean","Government":"Unitary one-party presidential republic","President":"Isaias Afwerki","Legislature":"National Assembly","Formation":"","Dʿmt":"c. 980 BC","Kingdom of Aksum":"c. 100 AD","Medri Bahri":"1137","Italian Eritrea":"1890","Eritrean Federation":"15 September 1952","De facto State of Eritrea":"24 May 1991","De jure State of Eritrea":"24 May 1993","Area":"","Total":"$5.352 billion[7]","Water (%)":"0.14%","Population":"","2016 estimate":"5,869,869[6] (116th)","Density":"51.8/km2 (134.2/sq mi) (154th)","GDP (PPP)":"2016 estimate","Per capita":"$771[7]","GDP (nominal)":"2016 estimate","HDI (2014)":"0.391[8]","Currency":"Nakfa (ERN)","Time zone":"EAT (UTC+3)","Summer (DST)":"not observed (UTC+3)","Drives on the":"right","Calling code":"+291","ISO 3166 code":"ER","Internet TLD":".er"}