{"Jamaica":"","undefined":"","Capital":"Kingston","Official languages":"English","National language":"Jamaican Patois (de facto)","Demonym":"Jamaican","Government":"Unitary parliamentary constitutional monarchy","Monarch":"Elizabeth II","Governor-General":"Patrick Allen","Prime Minister":"Andrew Holness","Legislature":"Parliament","Upper house":"Senate","Lower house":"House of Representatives","Independence from the United Kingdom":"","Granted":"6 August 1962","Area":"","Total":"$14.057 billion[2]","Water (%)":"1.5","Population":"","July 2015 estimate":"2,950,210[1] (139th)","Density":"268/km2 (694.1/sq mi) (49th)","GDP (PPP)":"2016 estimate","Per capita":"$4,968[2]","GDP (nominal)":"2016 estimate","Gini (2004)":"45.5[3]","HDI (2014)":"0.719[5]","Currency":"Jamaican dollar (JMD)","Time zone":"(UTC-5)","Drives on the":"left","Calling code":"+1-876","ISO 3166 code":"JM","Internet TLD":".jm"}