{"Mongolia":"","undefined":"","Capital":"Ulaanbaatar[a]","Official languages":"Mongolian","Official scripts":"Mongolian Cyrillic","Ethnic groups (2010)":"96% Mongols","Religion":"Buddhism (53%)","Demonym":"Mongol","Government":"Unitary semi-presidential republic[3][4][5]","President":"Tsakhiagiin Elbegdorj","Prime Minister":"Jargaltulgyn Erdenebat","Legislature":"State Great Khural","Formation":"","Xiongnu Empire":"formed 209 BC","Mongol Empire":"formed 1206","Declaration of independence from the Qing dynasty":"December 29, 1911","Mongolian People's Republic established":"November 26, 1924","Current Constitution":"February 13, 1992","Area":"","Total":"$12.5 billion","Water (%)":"0.43[6]","Population":"","2016 estimate":"3,081,677[7] (134th)","Density":"1.97[8]/km2 (5.1/sq mi) (238th)","GDP (PPP)":"2015 estimate","Per capita":"$4,353","GDP (nominal)":"2015 estimate","Gini (2011)":"36.5[9]","HDI (2014)":"0.727[10]","Currency":"Tögrög (MNT)","Time zone":"(UTC+7/+8[11])","Summer (DST)":"(UTC+8/+9[12])","Date format":"yyyy.mm.dd (CE)","Drives on the":"right","Calling code":"+976","ISO 3166 code":"MN","Internet TLD":".mn, .мон"}