{"New Zealand":"","undefined":"","Capital":"Wellington","Largest city":"Auckland","Official languages":"96.1% English[n 2][n 3]","Ethnic groups (2013)":"74.0% European","Demonym":"New Zealander","Government":"Unitary parliamentary constitutional monarchy","Monarch":"Elizabeth II","Governor-General":"Dame Patsy Reddy","Prime Minister":"Bill English","Chief Justice":"Dame Sian Elias","Legislature":"Parliament","Stages of Independence from the United Kingdom":"","Responsible government":"7 May 1856","Dominion":"26 September 1907","Statute of Westminster adopted":"25 November 1947","Area":"","Total":"$169.9 billion[8]","Water (%)":"1.6[n 4]","Population":"","2017 estimate":"4,773,970[7] (123rd)","2013 census":"4,242,048","Density":"17.5/km2 (45.3/sq mi) (205th)","GDP (PPP)":"2016 estimate","Per capita":"$36,254[8]","GDP (nominal)":"2016 estimate","Gini (2014)":"33.0[9]","HDI (2014)":"0.913[10]","Currency":"New Zealand dollar ($) (NZD)","Time zone":"NZST[n 5] (UTC+12)","Summer (DST)":"NZDT[n 6] (UTC+13)","Date format":"dd/mm/yyyy","Drives on the":"left","Calling code":"+64","ISO 3166 code":"NZ","Internet TLD":".nz"}